{"cameraMode":{"drawMode":0,"name":"Shaded","section":"Shading Mode"},"sceneLighting":false,"audioPlay":false,"sceneViewState":{"showFog":false,"showMaterialUpdate":false,"showSkybox":false,"showFlares":false,"showImageEffects":false,"showParticleSystems":false,"showVisualEffectGraphs":true,"m_FxEnabled":true},"in2DMode":false,"pivot":{"x":-2.300800323486328,"y":-7.111936569213867,"z":-1.17826247215271},"rotation":{"x":0.019248541444540025,"y":0.8038846254348755,"z":-0.02605331875383854,"w":0.5939120054244995},"size":1.3960530757904053,"orthographic":false}